RsNgx/RsNgx.py
RsNgx/__init__.py
RsNgx/enums.py
RsNgx/repcap.py
RsNgx/CustomFiles/__init__.py
RsNgx/CustomFiles/events.py
RsNgx/CustomFiles/utilities.py
RsNgx/Implementations/Apply.py
RsNgx/Implementations/__init__.py
RsNgx/Implementations/Arbitrary/Behavior.py
RsNgx/Implementations/Arbitrary/Fname.py
RsNgx/Implementations/Arbitrary/Priority.py
RsNgx/Implementations/Arbitrary/__init__.py
RsNgx/Implementations/Arbitrary/Block/Fname.py
RsNgx/Implementations/Arbitrary/Block/__init__.py
RsNgx/Implementations/Arbitrary/Sequence/Behavior.py
RsNgx/Implementations/Arbitrary/Sequence/Transfer.py
RsNgx/Implementations/Arbitrary/Sequence/__init__.py
RsNgx/Implementations/Arbitrary/Triggered/Group.py
RsNgx/Implementations/Arbitrary/Triggered/Point.py
RsNgx/Implementations/Arbitrary/Triggered/__init__.py
RsNgx/Implementations/Battery/__init__.py
RsNgx/Implementations/Battery/Model/Data.py
RsNgx/Implementations/Battery/Model/Fname.py
RsNgx/Implementations/Battery/Model/__init__.py
RsNgx/Implementations/Battery/Model/Current/Limit.py
RsNgx/Implementations/Battery/Model/Current/__init__.py
RsNgx/Implementations/Battery/Simulator/Capacity.py
RsNgx/Implementations/Battery/Simulator/Voc.py
RsNgx/Implementations/Battery/Simulator/__init__.py
RsNgx/Implementations/Battery/Simulator/Current/Limit.py
RsNgx/Implementations/Battery/Simulator/Current/__init__.py
RsNgx/Implementations/Calibration/Cancel.py
RsNgx/Implementations/Calibration/End.py
RsNgx/Implementations/Calibration/Point.py
RsNgx/Implementations/Calibration/Self.py
RsNgx/Implementations/Calibration/__init__.py
RsNgx/Implementations/Calibration/Ainput/Cancel.py
RsNgx/Implementations/Calibration/Ainput/End.py
RsNgx/Implementations/Calibration/Ainput/Start.py
RsNgx/Implementations/Calibration/Ainput/Umax.py
RsNgx/Implementations/Calibration/Ainput/Umin.py
RsNgx/Implementations/Calibration/Ainput/__init__.py
RsNgx/Implementations/Calibration/Current/Imax.py
RsNgx/Implementations/Calibration/Current/Imin.py
RsNgx-3.1.0.49.dist-info/METADATA
RsNgx-3.1.0.49.dist-info/WHEEL
RsNgx-3.1.0.49.dist-info/top_level.txt
RsNgx-3.1.0.49.dist-info/RECORD
