Metadata-Version: 2.1
Name: RsNgx
Version: 3.1.0.49
Summary: NGx Power Supply Remote-control Module
Home-page: UNKNOWN
Author: Rohde & Schwarz GmbH & Co. KG
License: MIT
Platform: UNKNOWN
Classifier: License :: OSI Approved :: MIT License
Classifier: Programming Language :: Python :: 3.6
Requires-Dist: PyVisa
